<chart  showvalues="0" caption="Quarterly Website  Visits (2010)" xaxisname="No of Visitor" yaxisname="Monthly share" animation="1" stack100percent="0" canvasbgangle="0" canvasborderthickness="2" chartleftmargin="5" chartrightmargin="15" charttopmargin="10" chartbottommargin="20" captionpadding="10" xaxisnamepadding="5" yaxisnamepadding="5" yaxisvaluespadding="2" labelpadding="3" basefontsize="13" outcnvbasefontsize="12" zeroplanealpha="80" zeroplanethickness="2" bgcolor="FFFFFF" bgalpha="100" showxaxispercentvalues="0" usepercentdistribution="1" plotgradientcolor="" basefont="Calibri" canvasbgcolor="FFFFFF" showalternatehgridcolor="0" alternatehgridcolor="FEEFED" divlinealpha="0" >
	<categories>
		<category label="Site A" widthpercent="40"/>
		<category label="Site B" widthpercent="15"/>
		<category label="Site C" widthpercent="15"/>
		<category label="Site D" widthpercent="15"/>
		<category label="Site E" widthpercent="15"/>
	</categories>
	<dataset seriesName="Jan" color="76EFB8" color_cc="76EFB8">
		<set value="10548"/>
		<set value="9550"/>
		<set value="9001"/>
		<set value="8120"/>
		<set value="7845"/>
	</dataset>
	<dataset seriesName="Feb" color_cc="92BACF" color="92BACF">
		<set value="12500"/>
		<set value="10800"/>
		<set value="9800"/>
		<set value="9080"/>
		<set value="8100"/>
	</dataset>
	<dataset seriesName="Mar" color="DBAEEE" color_cc="DBAEEE">
		<set value="13800"/>
		<set value="11930"/>
		<set value="10360"/>
		<set value="10769"/>
		<set value="9077"/>
	</dataset>
	</chart>
